{
  "ghostpanel_score": 100,
  "agent_readiness": null,
  "wcag_findings": [],
  "summary": "3/3 personas completed the task.",
  "meta": {
    "run_id": "0a5cea019903",
    "target_url": "http://localhost:8137/fixtures/hostile_form.html",
    "task": "Create an account and submit the sign-up form.",
    "generated_at": "2026-07-17T17:28:15.062216+00:00",
    "personas": 3
  },
  "stats": {
    "run": {
      "total_steps": 21,
      "total_duration_s": 94.9,
      "avg_latency_ms": 24192,
      "p95_latency_ms": 59333,
      "actions_by_type": {
        "click": 7,
        "write": 11,
        "scroll": 3
      },
      "blocked_actions": 0,
      "personas_succeeded": 3,
      "personas_abandoned": 0,
      "personas_errored": 0,
      "median_steps_to_abandon": null,
      "fastest_success_steps": 5
    },
    "personas": [
      {
        "persona_id": "low-vision",
        "persona_name": "Sam (low vision)",
        "outcome": "success",
        "steps": 11,
        "steps_survived": 11,
        "duration_s": 49.7,
        "avg_latency_ms": 17024,
        "actions_by_type": {
          "click": 5,
          "write": 5,
          "scroll": 1
        },
        "blocked_actions": 0,
        "max_repeated_action": 1,
        "perturbations": [
          "blur",
          "downscale"
        ]
      },
      {
        "persona_id": "tremor",
        "persona_name": "Dev (hand tremor)",
        "outcome": "success",
        "steps": 5,
        "steps_survived": 5,
        "duration_s": 22.6,
        "avg_latency_ms": 18876,
        "actions_by_type": {
          "click": 1,
          "write": 3,
          "scroll": 1
        },
        "blocked_actions": 0,
        "max_repeated_action": 1,
        "perturbations": [
          "tremor"
        ]
      },
      {
        "persona_id": "power-user",
        "persona_name": "Alex (power user)",
        "outcome": "success",
        "steps": 5,
        "steps_survived": 5,
        "duration_s": 22.6,
        "avg_latency_ms": 45275,
        "actions_by_type": {
          "click": 1,
          "write": 3,
          "scroll": 1
        },
        "blocked_actions": 0,
        "max_repeated_action": 1,
        "perturbations": []
      }
    ]
  },
  "survival_series": [
    {
      "step": 0,
      "alive": 3
    },
    {
      "step": 1,
      "alive": 3
    },
    {
      "step": 2,
      "alive": 3
    },
    {
      "step": 3,
      "alive": 3
    },
    {
      "step": 4,
      "alive": 3
    },
    {
      "step": 5,
      "alive": 3
    },
    {
      "step": 6,
      "alive": 3
    },
    {
      "step": 7,
      "alive": 3
    },
    {
      "step": 8,
      "alive": 3
    },
    {
      "step": 9,
      "alive": 3
    },
    {
      "step": 10,
      "alive": 3
    },
    {
      "step": 11,
      "alive": 3
    }
  ]
}